{
  "episode_id": "2026_1_23_五_Robotaxi上路_自駕AI大爆發 2026還能 買七巨頭嗎__早晨財經速",
  "podcast": "yutinghao",
  "created_at": "2026-02-21T14:17:23.535233",
  "summary_hash": "eb55acdb1c38",
  "status": "pending",
  "platforms": {
    "twitter": {
      "status": "pending",
      "content_file": "twitter.json",
      "image_file": null,
      "published_at": null,
      "post_ids": [],
      "error": null,
      "url": null
    },
    "threads": {
      "status": "pending",
      "content_file": "threads.json",
      "image_file": null,
      "published_at": null,
      "post_ids": [],
      "error": null,
      "url": null
    },
    "line": {
      "status": "pending",
      "content_file": "line.json",
      "image_file": null,
      "published_at": null,
      "post_ids": [],
      "error": null,
      "url": null
    },
    "instagram": {
      "status": "pending",
      "content_file": "instagram.json",
      "image_file": "instagram_card.png",
      "published_at": null,
      "post_ids": [],
      "error": null,
      "url": null
    },
    "telegram": {
      "status": "pending",
      "content_file": "telegram.json",
      "image_file": null,
      "published_at": null,
      "post_ids": [],
      "error": null,
      "url": null
    }
  }
}