{
  "thread": [
    {
      "text": "🎙️ 財經皓角 2026_3_9_一_Fed該壓通膨 還是拉就業_原油破百_恐慌來了嗎__早晨財經速解讀_ 重點整理\n\n📝 油價飆破 110 美元引發通膨與降息兩難，但游庭皓強調市場正經歷「大谷翔平式」的必要休息，投資者應區分短期外部衝擊與長期 AI 趨勢。\n\n💡 本集亮點：\n• 油價瘋狂飆升與能源供給瓶頸 西德州原油（WT...\n• 聯準會（Fed）與川普的「兩難困局」 美國 ...\n• 市場恐慌情緒與「均值回歸」 美股三大指數今年...\n\n👇 詳細內容請看回覆",
      "char_count": 383,
      "is_main": true
    },
    {
      "text": "💡 本集重點：\n\n• 油價瘋狂飆升與能源供給瓶頸 西德州原油（WTI）飆升至每桶 111 美元，主因是中東衝突導致荷姆茲海峽航運停擺。摩根大通報告指出，由於無法出口，中東各國儲...\n• 聯準會（Fed）與川普的「兩難困局」 美國 2 月非農就業數據意外下滑 9.2 萬人（遠低於預期的增加 5 萬人），失業率升至 4.4%，顯示經濟有降息需...\n• 市場恐慌情緒與「均值回歸」 美股三大指數今年轉為負報酬，VIX 指數衝上 30。游庭皓分析，過去漲多的 AI 硬體股（如費半）正在進行估值修正，而過去跌深...",
      "char_count": 429,
      "is_main": false
    },
    {
      "text": "💬 游庭皓金句：\n「左側不悲觀，右側不會過度樂觀。隨著左側（下跌）的產生，機會就開始出現。」\n\n#游庭皓 #投資 #理財",
      "char_count": 101,
      "is_main": false
    }
  ],
  "total_tweets": 3,
  "hashtags": [
    "#游庭皓",
    "#投資",
    "#理財"
  ],
  "cashtags": []
}